os_mfa/__init__.py
os_mfa/__main__.py
os_mfa/clouds_configs.py
os_mfa/tokens.py
os_mfa-0.4.2.dist-info/LICENSE
os_mfa-0.4.2.dist-info/METADATA
os_mfa-0.4.2.dist-info/WHEEL
os_mfa-0.4.2.dist-info/entry_points.txt
os_mfa-0.4.2.dist-info/top_level.txt
os_mfa-0.4.2.dist-info/RECORD
