Metadata-Version: 2.1
Name: os-mfa
Version: 0.4.2
Summary: A minimal utility for managing cli authentication with openstack more securely and conveniently
Author-email: Simon Merrick <s.m3rrick@gmail.com>
Project-URL: Homepage, https://github.com/iokiwi/os-mfa
Keywords: openstack,mfa,auth
Classifier: License :: OSI Approved :: MIT License
Classifier: Programming Language :: Python
Classifier: Programming Language :: Python :: 3
Requires-Python: >=3.6
License-File: LICENSE
Requires-Dist: requests
Requires-Dist: PyYaml
Requires-Dist: python-dateutil
Provides-Extra: dev
Requires-Dist: black ; extra == 'dev'
Requires-Dist: bumpver ; extra == 'dev'
Requires-Dist: pip-tools ; extra == 'dev'
Requires-Dist: twine ; extra == 'dev'
Requires-Dist: build ; extra == 'dev'
Requires-Dist: mypy ; extra == 'dev'
